datanator_query/VERSION
datanator_query/__init__.py
datanator_query/config/__init__.py
datanator_query/config/config.py
datanator_query/query/__init__.py
datanator_query/query/front_end_query.py
datanator_query/query/metabolite_query.py
datanator_query/query/query_basic_users.py
datanator_query/query/query_kegg_orthology.py
datanator_query/query/query_metabolites_meta.py
datanator_query/query/query_nosql.py
datanator_query/query/query_pax.py
datanator_query/query/query_protein.py
datanator_query/query/query_sabiork.py
datanator_query/query/query_taxon_tree.py
datanator_query/query/query_uniprot.py
datanator_query-0.1.dist-info/LICENSE
datanator_query-0.1.dist-info/METADATA
datanator_query-0.1.dist-info/WHEEL
datanator_query-0.1.dist-info/entry_points.txt
datanator_query-0.1.dist-info/top_level.txt
datanator_query-0.1.dist-info/RECORD
